aws_ec2_auto_scaling_instance_running_scheduler/__init__.py
aws_ec2_auto_scaling_instance_running_scheduler/py.typed
aws_ec2_auto_scaling_instance_running_scheduler/_jsii/__init__.py
aws_ec2_auto_scaling_instance_running_scheduler/_jsii/aws-ec2-auto-scaling-instance-running-scheduler@0.2.5.jsii.tgz
aws_ec2_auto_scaling_instance_running_scheduler-0.2.5.dist-info/LICENSE
aws_ec2_auto_scaling_instance_running_scheduler-0.2.5.dist-info/METADATA
aws_ec2_auto_scaling_instance_running_scheduler-0.2.5.dist-info/WHEEL
aws_ec2_auto_scaling_instance_running_scheduler-0.2.5.dist-info/top_level.txt
aws_ec2_auto_scaling_instance_running_scheduler-0.2.5.dist-info/RECORD
